{
    "relationships": [
        {
            "relationshipName": "strategymbrlhs",
            "otherEntityName": "strategymbr",
            "relationshipType": "one-to-many",
            "otherEntityRelationshipName": "strategylhs"
        },
		{
            "relationshipName": "strategymbrhs",
            "otherEntityName": "strategymbr",
            "relationshipType": "one-to-many",
            "otherEntityRelationshipName": "strategyrhs"
        }
    ],
    "fields": [
        {
            "fieldName": "name",
            "fieldType": "String",
            "fieldValidateRules": [
                "required",
                "maxlength"
            ],
            "fieldValidateRulesMaxlength": "100"
        },
        {
            "fieldName": "description",
            "fieldType": "String",
            "fieldValidateRules": [
                "required",
                "maxlength"
            ],
            "fieldValidateRulesMaxlength": "255"
        },
        {
            "fieldName": "status",
            "fieldType": "String",
            "fieldValidateRules": [
                "required",
                "maxlength"
            ],
            "fieldValidateRulesMaxlength": "25"
        },
        {
            "fieldName": "lastmodifiedby",
            "fieldType": "String",
            "fieldValidateRules": [
                "required",
                "maxlength"
            ],
            "fieldValidateRulesMaxlength": "50"
        },
        {
            "fieldName": "lastmodifieddatetime",
            "fieldType": "ZonedDateTime",
            "fieldValidateRules": [
                "required"
            ]
        },
        {
            "fieldName": "domain",
            "fieldType": "String",
            "fieldValidateRules": [
                "required",
                "maxlength"
            ],
            "fieldValidateRulesMaxlength": "25"
        }
    ],
    "changelogDate": "20160509235551",
    "dto": "no",
    "service": "no",
    "entityTableName": "strategy",
    "pagination": "pagination",
    "microserviceName": "adap_core",
    "searchEngine": "elasticsearch"
}
